nitrado_api/__init__.py
nitrado_api/nitrado_api.py
nitrado_api-0.2.dist-info/LICENCE
nitrado_api-0.2.dist-info/METADATA
nitrado_api-0.2.dist-info/WHEEL
nitrado_api-0.2.dist-info/top_level.txt
nitrado_api-0.2.dist-info/RECORD
