Metadata-Version: 2.1
Name: nitrado_api
Version: 0.2
Summary: Python module to interact with Nitrado API endpoints.
Home-page: https://github.com/DonMatraca/nitrado_api
Author: DonMatraca
Author-email: r.gallogomez@gmail.com
Classifier: Programming Language :: Python :: 3
Classifier: License :: OSI Approved :: MIT License
Classifier: Operating System :: OS Independent
Requires-Python: >=3.6
License-File: LICENCE
Requires-Dist: aiohttp
